confocal_raytracer/__init__.py
confocal_raytracer/analysis.py
confocal_raytracer/data/n_intensity_500_800_new.csv
confocal_raytracer/figures/image.png
confocal_raytracer/load_data.py
confocal_raytracer/simulation/_utils.py
confocal_raytracer/simulation/aspheric.py
confocal_raytracer/simulation/launcher.py
confocal_raytracer/simulation/ray.py
confocal_raytracer/simulation/raytrace.py
confocal_raytracer/simulation/setup.py
confocal_raytracer-0.1.34.dist-info/METADATA
confocal_raytracer-0.1.34.dist-info/WHEEL
confocal_raytracer-0.1.34.dist-info/RECORD
